infi.asi_utils-0.2.11-py2.7-nspkg.pth
infi/asi_utils/__init__.py
infi/asi_utils/__version__.py
infi/asi_utils/formatters.py
infi.asi_utils-0.2.11.dist-info/LICENSE
infi.asi_utils-0.2.11.dist-info/METADATA
infi.asi_utils-0.2.11.dist-info/WHEEL
infi.asi_utils-0.2.11.dist-info/entry_points.txt
infi.asi_utils-0.2.11.dist-info/namespace_packages.txt
infi.asi_utils-0.2.11.dist-info/top_level.txt
infi.asi_utils-0.2.11.dist-info/RECORD
