Metadata-Version: 2.1
Name: infi.asi-utils
Version: 0.2.11
Summary: an alternative to sg3-utils
Home-page: https://git.infinidat.com/host-opensource/infi.asi_utils
Author: Arnon Yaari
Author-email: arnony@infinidat.com
License: BSD
Platform: UNKNOWN
Classifier: Intended Audience :: Developers
Classifier: Intended Audience :: System Administrators
Classifier: License :: OSI Approved :: BSD License
Classifier: Operating System :: OS Independent
Classifier: Programming Language :: Python
Classifier: Programming Language :: Python :: 2
Classifier: Programming Language :: Python :: 3
Classifier: Topic :: Software Development :: Libraries :: Python Modules
Requires-Dist: docopt
Requires-Dist: hexdump
Requires-Dist: infi.asi (>=0.3.33)
Requires-Dist: infi.os-info
Requires-Dist: infi.pyutils
Requires-Dist: infi.sgutils
Requires-Dist: setuptools
